packaging_demo/__init__.py
packaging_demo/colorized_demo.py
packaging_demo/my_file.py
packaging_demo/my_other_file.py
packaging_demo/states_info.py
packaging_demo/my_folder/__init__.py
packaging_demo/my_folder/cities.json
packaging_demo/my_folder/my_nested_file.py
packaging_demo_bobo-0.0.2.dist-info/METADATA
packaging_demo_bobo-0.0.2.dist-info/WHEEL
packaging_demo_bobo-0.0.2.dist-info/top_level.txt
packaging_demo_bobo-0.0.2.dist-info/RECORD
