Metadata-Version: 2.1
Name: packaging-demo-bobo
Version: 0.0.2
Summary: a simple package for packaging
Author-email: ouss <ouss@brown.edu>
Classifier: Programming Language :: Python :: 3
Requires-Python: >=3.8
Requires-Dist: fastapi
Requires-Dist: numpy
Provides-Extra: dev
Requires-Dist: packaging-demo[release,static-code-qa,test] ; extra == 'dev'
Provides-Extra: release
Requires-Dist: build ; extra == 'release'
Requires-Dist: twine ; extra == 'release'
Provides-Extra: static-code-qa
Requires-Dist: pre-commit ; extra == 'static-code-qa'
Provides-Extra: test
Requires-Dist: pytest ; extra == 'test'
Requires-Dist: pytest-cov ; extra == 'test'
